thl_phonetic_transliteration/__init__.py
thl_phonetic_transliteration/transliterator.py
thl_phonetic_transliteration-0.2.4.dist-info/METADATA
thl_phonetic_transliteration-0.2.4.dist-info/WHEEL
thl_phonetic_transliteration-0.2.4.dist-info/licenses/LICENSE
thl_phonetic_transliteration-0.2.4.dist-info/RECORD
