Metadata-Version: 2.3
Name: thl_phonetic_transliteration
Version: 0.2.4
Summary: The goal of this code is to provide a library to convert Tibetan unicode and Wylie transliterations to THL Simplified Phonetic Transliteration.
Project-URL: Homepage, https://github.com/billingsmoore/MLotsawa
Project-URL: Issues, https://github.com/billingsmoore/MLotsawa/issues
Author-email: billingsmoore <billingsmoore@gmail.com>
License-File: LICENSE
Classifier: License :: OSI Approved :: MIT License
Classifier: Operating System :: OS Independent
Classifier: Programming Language :: Python :: 3
Requires-Python: >=3.8
Requires-Dist: mlotsawa
